allusgov/__init__.py
allusgov/__main__.py
allusgov/allusgov.py
allusgov/cli.py
allusgov/cli_options.py
allusgov/dev.py
allusgov/exporter/__init__.py
allusgov/exporter/exporter.py
allusgov/importer/__init__.py
allusgov/importer/importer.py
allusgov/importer/samgov_importer.py
allusgov/merger/__init__.py
allusgov/merger/merger.py
allusgov/processor/__init__.py
allusgov/processor/normalize_name.py
allusgov/processor/processor.py
allusgov/processor/words/2of12inf.txt
allusgov/processor/words/person-names.txt
allusgov/processor/words/place-names.txt
allusgov/settings.py
allusgov/spider/__init__.py
allusgov/spider/acronyms.py
allusgov/spider/budget.py
allusgov/spider/cisagov.py
allusgov/spider/federalregister.py
allusgov/spider/opmgov.py
allusgov/spider/samgov.py
allusgov/spider/settings.py
allusgov/spider/usagov.py
allusgov/spider/usaspending.py
allusgov/spider/usgovmanual.py
allusgov/tests/__init__.py
allusgov/tests/conftest.py
allusgov/tests/test_utils.py
allusgov/utils/__init__.py
allusgov/utils/utils.py
allusgov-0.0.dist-info/LICENSE
allusgov-0.0.dist-info/METADATA
allusgov-0.0.dist-info/WHEEL
allusgov-0.0.dist-info/entry_points.txt
allusgov-0.0.dist-info/RECORD
