Metadata-Version: 2.1
Name: allusgov
Version: 0.0
Summary: This project attempts to map the organization of the US Federal Government by gathering and consolidating information from various directories.
Home-page: https://pypi.org/project/allusgov
License: GPL-3.0-or-later
Author: Owen Barton
Author-email: owen.barton@civicactions.com
Requires-Python: >=3.10,<3.12
Classifier: Development Status :: 1 - Planning
Classifier: License :: OSI Approved :: GNU General Public License v3 or later (GPLv3+)
Classifier: Natural Language :: English
Classifier: Operating System :: OS Independent
Classifier: Programming Language :: Python
Classifier: Programming Language :: Python :: 3
Classifier: Programming Language :: Python :: 3.10
Classifier: Programming Language :: Python :: 3.11
Classifier: Programming Language :: Python :: 3
Classifier: Programming Language :: Python :: 3.11
Requires-Dist: beautifulsoup4 (>=4.12.2,<5.0.0)
Requires-Dist: bigtree[image] (>=0.9.1,<0.10.0)
Requires-Dist: click
Requires-Dist: click-log (>=0.4.0,<0.5.0)
Requires-Dist: flatten-json (>=0.1.13,<0.2.0)
Requires-Dist: lxml (>=4.9.2,<5.0.0)
Requires-Dist: natsort (>=8.3.1,<9.0.0)
Requires-Dist: networkx[default] (>=3.0,<4.0)
Requires-Dist: nltk (>=3.8.1,<4.0.0)
Requires-Dist: polars (>=0.16.18,<0.17.0)
Requires-Dist: python-dotenv (>=1.0.0,<2.0.0)
Requires-Dist: questionary (>=1.10.0,<2.0.0)
Requires-Dist: rapidfuzz (>=2.15.0,<3.0.0)
Requires-Dist: scrapy (>=2.8.0,<3.0.0)
Requires-Dist: spacy (>=3.5.1,<4.0.0)
Requires-Dist: xlsx2csv (>=0.8.1,<0.9.0)
Project-URL: Repository, https://github.com/civicactions/allusgov
